README.md
setup.cfg
setup.py
distributionGauss/Binomialdistribution.py
distributionGauss/Gaussiandistribution.py
distributionGauss/Generaldistribution.py
distributionGauss/__init__.py
distributionGauss.egg-info/PKG-INFO
distributionGauss.egg-info/SOURCES.txt
distributionGauss.egg-info/dependency_links.txt
distributionGauss.egg-info/not-zip-safe
distributionGauss.egg-info/top_level.txt